{"kind":"identitytoolkit#DownloadAccountResponse","users":[{"localId":"lSkf5FPqsRJ5Pjc1idKibPOmIZ14","lastLoginAt":"1749868456621","emailVerified":false,"email":"tpinto@nur.edu.bot","salt":"fakeSaltmTMbdTONmkXkFTJvN6Rt","passwordHash":"fakeHash:salt=fakeSaltmTMbdTONmkXkFTJvN6Rt:password=Nur123456","passwordUpdatedAt":1749868456621,"validSince":"1749868456","createdAt":"1749868456621","providerUserInfo":[{"providerId":"password","email":"tpinto@nur.edu.bot","federatedId":"tpinto@nur.edu.bot","rawId":"tpinto@nur.edu.bot"}],"lastRefreshAt":"2025-06-14T02:34:16.622Z"}]}